dope/__init__.py
dopelines-0.1.1.dist-info/LICENSE
dopelines-0.1.1.dist-info/METADATA
dopelines-0.1.1.dist-info/WHEEL
dopelines-0.1.1.dist-info/top_level.txt
dopelines-0.1.1.dist-info/RECORD
