Metadata-Version: 2.1
Name: dopelines
Version: 0.1.1
Summary: Douglas-Peucker line simplification
Author-email: dennisvang <djvg@protonmail.com>
License: MIT License
Project-URL: source, https://github.com/dennisvang/dope
Project-URL: issues, https://github.com/dennisvang/dope/issues
Classifier: Programming Language :: Python :: 3
Classifier: License :: OSI Approved :: MIT License
Classifier: Operating System :: OS Independent
Requires-Python: >=3.8
License-File: LICENSE
Requires-Dist: numpy
Provides-Extra: dev
Requires-Dist: black ; extra == 'dev'
Requires-Dist: build ; extra == 'dev'
Requires-Dist: twine ; extra == 'dev'
Provides-Extra: plot
Requires-Dist: matplotlib ; extra == 'plot'
